jdgenometracks/MPLPlotter.py
jdgenometracks/PlotlyPlotter.py
jdgenometracks/__init__.py
jdgenometracks/utils.py
jdgenometracks/tracks/BedGraphTrack.py
jdgenometracks/tracks/BedTrack.py
jdgenometracks/tracks/GenomeTrack.py
jdgenometracks/tracks/SpacerTrack.py
jdgenometracks/tracks/XAxisTrack.py
jdgenometracks/tracks/__init__.py
jdgenometracks-0.2.1.dist-info/METADATA
jdgenometracks-0.2.1.dist-info/WHEEL
jdgenometracks-0.2.1.dist-info/top_level.txt
jdgenometracks-0.2.1.dist-info/RECORD
