Metadata-Version: 2.1
Name: jdgenometracks
Version: 0.2.1
Summary: A Python package for plotting genomic data.
Author-email: Justin Delano <jdelano@g.harvard.edu>
Project-URL: Homepage, https://github.com/justin-delano/jdgenometracks
Requires-Python: >=3.8
Requires-Dist: pandas
Requires-Dist: numpy
Requires-Dist: matplotlib
Requires-Dist: plotly >=5.3.0
Requires-Dist: scipy
Provides-Extra: dev
Requires-Dist: black ; extra == 'dev'
Requires-Dist: isort ; extra == 'dev'
